boLogger/__init__.py
boLogger/boLogger.py
bologger-0.1.5.0.dist-info/LICENSE
bologger-0.1.5.0.dist-info/METADATA
bologger-0.1.5.0.dist-info/WHEEL
bologger-0.1.5.0.dist-info/RECORD
