Metadata-Version: 2.1
Name: boLogger
Version: 0.1.5.0
Summary: An advanced logging system used for clear understanding of your logs.
Home-page: https://github.com/Bernso/boLogger
License: MIT
Keywords: Logger,Clear,Colourfull,Inputs
Author: Bernso
Author-email: Bernso@duck.com
Requires-Python: >=3.8,<4.0
Classifier: License :: OSI Approved :: MIT License
Classifier: Programming Language :: Python :: 3
Classifier: Programming Language :: Python :: 3.8
Classifier: Programming Language :: Python :: 3.9
Classifier: Programming Language :: Python :: 3.10
Classifier: Programming Language :: Python :: 3.11
Classifier: Programming Language :: Python :: 3.12
Classifier: Programming Language :: Python :: 3.13
Project-URL: Repository, https://github.com/Bernso/boLogger
